virus_fitness/__init__.py
virus_fitness/usa.py
virus_fitness-0.1.0.dist-info/METADATA
virus_fitness-0.1.0.dist-info/WHEEL
virus_fitness-0.1.0.dist-info/top_level.txt
virus_fitness-0.1.0.dist-info/RECORD
