Metadata-Version: 2.4
Name: virus_fitness
Version: 0.1.0
Summary: A package for virus fitness estimation using MLR model
Author: USER01
Requires-Python: >=3.7
Requires-Dist: pandas
Requires-Dist: numpy
Requires-Dist: tensorflow
Requires-Dist: matplotlib
Provides-Extra: test
Requires-Dist: pytest; extra == "test"
Dynamic: requires-python
